{
    "data": [
        {
            "chi_name": "文湖線",
            "search_name": ["文湖線"],
            "alias": [
                "文湖線",
                "文山內湖線",
                "木柵線",
                "文山線",
                "內湖線"
            ],
            "route_code": "BR",
            "image_route": "tp_wenhu_map.JPG",
            "description": "文湖線是台北捷運的一條路線，於1996年通車，2009年全線通車。是台北捷運的第一條路線，服務木柵、大安、大直、內湖與南港地區。"
        },
        {
            "chi_name": "淡水信義線",
            "search_name": ["淡水信義線", "淡水線", "信義線"],
            "alias": [
                "淡水信義線",
                "淡水線",
                "信義線"
            ],
            "route_code": "R",
            "image_route": "tp_tamsui_map.png",
            "description": "淡水信義線是台北捷運的一條路線，於1997年淡水線通車，2012年信義線通車。是目前台北捷運仍在建設中的唯一高運量路網。最後一段延伸段「信義線東延段」預計於2023年通車。"
        },
        {
            "chi_name": "松山新店線",
            "search_name": ["松山新店線", "松山線", "新店線"],
            "alias": [
                "松山新店線",
                "松山線",
                "新店線",
                "小南門線"
            ],
            "route_code": "G",
            "image_route": "tp_green_map.jpg",
            "description": "松山新店線是台北捷運的一條路線，於1998年新店線通車，2014年松山線通車，並附有一條支線小碧潭支線。"
        },
        {
            "chi_name": "中和新蘆線",
            "search_name": ["中和線", "新莊線", "蘆洲線", "中和新蘆線"],
            "alias": [
                "中和線",
                "新莊線",
                "蘆洲線",
                "中和新蘆線"
            ],
            "route_code": "O",
            "image_route": "tp_orange_map.png",
            "description": "中和新蘆線是台北捷運的一條路線，於1998年中和線通車，2013年新莊線全線通車。"
        },
        {
            "chi_name": "板南線",
            "search_name": ["板南線"],
            "alias": [
                "板南線",
                "南港線",
                "板橋線",
                "土城線"
            ],
            "route_code": "BL",
            "image_route": "tp_blue_map.png",
            "description": "板南線是台北捷運的一條路線，於1999年通車，2016年全線通車。是目前台北捷運客運量最高的路線。"
        },
        {
            "chi_name": "環狀線",
            "search_name": ["環狀線"],
            "alias": [
                "環狀線",
                "環狀線西環段",
                "環狀線北環段",
                "環狀線東環段",
                "環狀線南環段",
                "環狀線南北環",
                "環狀線南北環段",
                "南北線",
                "西環段",
                "北環段",
                "南環段",
                "東環段"
            ],
            "route_code": "Y",
            "image_route": "tp_circular_map.png",
            "description": "環狀線是臺北捷運的一條環狀路線，西環段於2020年通車，南環段與北環段目前正施工中，預計2030年通車。東環段則在規劃中，預定綜合規劃核定後8年內完工。"
        },
        {
            "chi_name": "萬大樹林線",
            "search_name": ["萬大線"],
            "alias": [
                "萬大樹林線",
                "萬大中和樹林線",
                "萬大線",
                "樹林線"
            ],
            "route_code": "LG",
            "image_route": "tp_lightgreen_map.jfif",
            "description": "萬大樹林線是台北捷運興建中的一條路線，分為兩階段施工。第一階段為萬大線，預計2025年完工。第二階段為樹林線，已於2022年末開始施工，預計6年後完工。"
        },
        {
            "chi_name": "民生汐止線",
            "search_name": ["民生汐止線", "汐東線"],
            "alias": [
                "民生汐止線",
                "汐東線",
                "汐東捷運"
            ],
            "route_code": "SB",
            "image_route": "tp_xizhi_map.png",
            "description": "民生汐止線是台北捷運規劃中的一條路線，目前預計與基隆捷運進行整合，整案正在規劃中。預計分為兩階段施工，第一階段施作東湖站以東至汐止區公所路段，第二階段為東湖站以西路線。"
        }
    ]
}